maker/__init__.py
maker/maker.py
menu_maker-0.5.2.dist-info/LICENSE
menu_maker-0.5.2.dist-info/METADATA
menu_maker-0.5.2.dist-info/WHEEL
menu_maker-0.5.2.dist-info/top_level.txt
menu_maker-0.5.2.dist-info/RECORD
