Metadata-Version: 2.1
Name: menu-maker
Version: 0.5.2
Summary: Library for generating and running menus, for use in shell (terminal) programs.
Home-page: https://github.com/AgentNumber47/menu_maker
Author: AgentNumber47
Author-email: author@example.com
License: UNKNOWN
Platform: UNKNOWN
Classifier: Programming Language :: Python :: 3
Classifier: License :: OSI Approved :: MIT License
Classifier: Operating System :: OS Independent
Requires-Python: >=3.6
License-File: LICENSE
